pyusbcameraindex-1.0.1.dist-info/METADATA
pyusbcameraindex-1.0.1.dist-info/WHEEL
pyusbcameraindex-1.0.1.dist-info/licenses/LICENSE
pyusbcameraindex/__init__.py
pyusbcameraindex/directshow.py
pyusbcameraindex-1.0.1.dist-info/RECORD
