Metadata-Version: 2.1
Name: pyusbcameraindex
Version: 1.0.1
Summary: Identify and select your USB cameras in Python for use with OpenCV.
Keywords: opencv,python,usb,directshow,index
Author: John Hardy
License: Copyright 2024 (Dr. John Hardy)
Classifier: Programming Language :: Python :: 3
Classifier: License :: OSI Approved :: MIT License
Classifier: Operating System :: Microsoft :: Windows
Project-URL: Homepage, https://github.com/JohnHardy/pyusbcameraindex
Project-URL: Repository, https://github.com/JohnHardy/pyusbcameraindex
Project-URL: Bug tracker, https://github.com/JohnHardy/pyusbcameraindex/issues
Requires-Python: >=3.10
Requires-Dist: comtypes>=1.4.4
Requires-Dist: pywin32>=306
